dsn/__init__.py
dsn/main.py
dsn/bitgrit/__init__.py
dsn/bitgrit/datasets/__init__.py
dsn/bitgrit/datasets/dataset.py
dsn/bitgrit/datasets/helper.py
dsn/bitgrit/gcp/__init__.py
dsn/bitgrit/gcp/create_dataset_pd.py
dsn/bitgrit/gcp/dataset_api.py
dsn/bitgrit/gcp/tests/__init__.py
dsn/bitgrit/gcp/tests/test_dataset_api.py
bitgrit_cloud-0.0.3.dist-info/LICENSE
bitgrit_cloud-0.0.3.dist-info/METADATA
bitgrit_cloud-0.0.3.dist-info/WHEEL
bitgrit_cloud-0.0.3.dist-info/top_level.txt
bitgrit_cloud-0.0.3.dist-info/RECORD
